olxsearch/__init__.py
olxsearch/__main__.py
olxsearch/olxsearch.py
olxsearch/olxsearchargentina.py
olxsearch/olxsearchbosnia.py
olxsearch/olxsearchbrazil.py
olxsearch/olxsearchbulgaria.py
olxsearch/olxsearchcolombia.py
olxsearch/olxsearchecuador.py
olxsearch/olxsearchegypt.py
olxsearch/olxsearchguatemala.py
olxsearch/olxsearchindia.py
olxsearch/olxsearchindonesia.py
olxsearch/olxsearchkazakhstan.py
olxsearch/olxsearchlebanon.py
olxsearch/olxsearchoman.py
olxsearch/olxsearchpakistan.py
olxsearch/olxsearchpanama.py
olxsearch/olxsearchperu.py
olxsearch/olxsearchpoland.py
olxsearch/olxsearchportugal.py
olxsearch/olxsearchromania.py
olxsearch/olxsearchsansalvador.py
olxsearch/olxsearchsouthafrica.py
olxsearch/olxsearchukraine.py
olxsearch/olxsearchuzbekistan.py
olxsearch/base/__init__.py
olxsearch/base/olxsearchbase.py
olxsearch/base/olxsearchbasea.py
olxsearch/base/olxsearchbaseb.py
olxsearch/base/olxsearchbasec.py
olxsearch/base/olxsearchbased.py
olxsearch/base/olxsearchbasee.py
olxsearch-1.0.6.dist-info/LICENSE
olxsearch-1.0.6.dist-info/METADATA
olxsearch-1.0.6.dist-info/WHEEL
olxsearch-1.0.6.dist-info/entry_points.txt
olxsearch-1.0.6.dist-info/top_level.txt
olxsearch-1.0.6.dist-info/RECORD
