Metadata-Version: 2.1
Name: olxsearch
Version: 1.0.6
Summary: Download small ad listings from OLX marketplaces"
Home-page: https://gitlab.com/christoph.fink/olxsearch
Author: Christoph Fink
Author-email: christoph.fink@helsinki.fi
License: GPLv3
Platform: UNKNOWN
Classifier: Programming Language :: Python :: 3
Classifier: License :: OSI Approved :: GNU General Public License v3 (GPLv3)
Classifier: Operating System :: OS Independent
Requires-Dist: beautifulsoup4
Requires-Dist: dateparser
Requires-Dist: fake-useragent
Requires-Dist: GeoAlchemy2
Requires-Dist: geocoder
Requires-Dist: pandas
Requires-Dist: requests
Requires-Dist: SQLAlchemy (>=1.4.0b1)
